rtl/apb_slave.v
`timescale 1ns/1ps
//============================================================
// Module : apb_slave
// Description : APB3 Slave Interface
// Author : Mihir
//============================================================

module apb_slave(

    input wire PCLK,
    input wire PRESETn,

    input wire PSEL,
    input wire PENABLE,
    input wire PWRITE,

    input wire [7:0] PADDR,
    input wire [31:0] PWDATA,

    output reg [31:0] PRDATA,
    output reg PREADY,

    //--------------------------------------------------------
    // Counter
    //--------------------------------------------------------

    input wire [7:0] counter_value,

    //--------------------------------------------------------
    // ALU
    //--------------------------------------------------------

    output reg [7:0] alu_a,
    output reg [7:0] alu_b,
    output reg [2:0] alu_opcode,

    input wire [7:0] alu_result,

    //--------------------------------------------------------
    // Timer
    //--------------------------------------------------------

    output reg [7:0] timer_load,

    output reg timer_start,
    output reg timer_enable,

    input wire timer_done,
    input wire timer_running,

    //--------------------------------------------------------
    // GPIO
    //--------------------------------------------------------

    output reg [7:0] gpio_direction,
    output reg [7:0] gpio_write,

    input wire [7:0] gpio_read

);

//------------------------------------------------------------
// APB WRITE
//------------------------------------------------------------

always @(posedge PCLK or negedge PRESETn)

begin

    if(!PRESETn)

    begin

        alu_a <= 0;
        alu_b <= 0;
        alu_opcode <= 0;

        timer_load <= 0;
        timer_start <= 0;
        timer_enable <= 0;

        gpio_direction <= 0;
        gpio_write <= 0;

        PREADY <= 0;

    end

    else

    begin

        PREADY <= 0;
        timer_start <= 0;

        if(PSEL && PENABLE)

        begin

            PREADY <= 1;

            if(PWRITE)

            begin

                case(PADDR)

                8'h04:
                    alu_a <= PWDATA[7:0];

                8'h08:
                    alu_b <= PWDATA[7:0];

                8'h0C:
                    alu_opcode <= PWDATA[2:0];

                8'h14:
                    timer_load <= PWDATA[7:0];

                8'h18:

                begin
                    timer_start <= PWDATA[0];
                    timer_enable <= PWDATA[1];
                end

                8'h20:
                    gpio_direction <= PWDATA[7:0];

                8'h24:
                    gpio_write <= PWDATA[7:0];

                endcase

            end

        end

    end

end

//------------------------------------------------------------
// APB READ
//------------------------------------------------------------

always @(*)

begin

    PRDATA = 32'h00000000;

    if(PSEL && !PWRITE)

    begin

        case(PADDR)

        8'h00:
            PRDATA = {24'h0,counter_value};

        8'h10:
            PRDATA = {24'h0,alu_result};

        8'h1C:
            PRDATA = {30'b0,timer_running,timer_done};

        8'h28:
            PRDATA = {24'h0,gpio_read};

        default:
            PRDATA = 32'h00000000;

        endcase

    end

end

endmodule

rtl/gpio.v
`timescale 1ns/1ps
//============================================================
// Module : gpio
// Description : Parameterized GPIO Peripheral
// Author : Mihir
//============================================================

module gpio #(
    parameter WIDTH = 8
)(
    input  wire                 clk,
    input  wire                 rst,

    input  wire                 write_enable,

    input  wire [WIDTH-1:0]     direction,
    input  wire [WIDTH-1:0]     write_data,

    input  wire [WIDTH-1:0]     gpio_in,

    output reg  [WIDTH-1:0]     gpio_out,
    output wire [WIDTH-1:0]     gpio_read
);

integer i;

//------------------------------------------------------------
// Output Register
//------------------------------------------------------------

always @(posedge clk) begin

    if(rst)
        gpio_out <= {WIDTH{1'b0}};

    else if(write_enable)
        gpio_out <= write_data;

end

//------------------------------------------------------------
// Read Logic
//------------------------------------------------------------

generate

genvar k;

for(k=0;k<WIDTH;k=k+1)

begin : GPIO_READ

assign gpio_read[k] = direction[k] ?
                      gpio_out[k] :
                      gpio_in[k];

end

endgenerate

endmodule

rtl/timer.v
`timescale 1ns/1ps
//============================================================
// Module : timer
// Description : Parameterized Countdown Timer IP
// Author : Mihir
//============================================================

module timer #(
    parameter WIDTH = 8
)(
    input  wire                 clk,
    input  wire                 rst,

    input  wire                 start,
    input  wire                 enable,

    input  wire [WIDTH-1:0]     load_value,

    output reg  [WIDTH-1:0]     count,
    output reg                  done,
    output reg                  running
);

//------------------------------------------------------------
// Timer Logic
//------------------------------------------------------------

always @(posedge clk) begin

    //--------------------------------------------------------
    // Reset
    //--------------------------------------------------------

    if (rst) begin
        count   <= {WIDTH{1'b0}};
        done    <= 1'b0;
        running <= 1'b0;
    end

    //--------------------------------------------------------
    // Start Timer
    //--------------------------------------------------------

    else if (start) begin
        count   <= load_value;
        running <= 1'b1;
        done    <= 1'b0;
    end

    //--------------------------------------------------------
    // Timer Running
    //--------------------------------------------------------

    else if (running && enable) begin

        if (count > 0) begin
            count <= count - 1'b1;
            done  <= 1'b0;
        end

        else begin
            running <= 1'b0;
            done    <= 1'b1;
        end

    end

    //--------------------------------------------------------
    // Hold State
    //--------------------------------------------------------

    else begin
        count   <= count;
        running <= running;
        done    <= done;
    end

end

endmodule

rtl/alu.v
`timescale 1ns/1ps
//============================================================
// Module : alu
// Description : Parameterized Arithmetic Logic Unit
// Author : Mihir
//============================================================

module alu #(
    parameter WIDTH = 8
)(
    input  wire [WIDTH-1:0] a,
    input  wire [WIDTH-1:0] b,
    input  wire [2:0] opcode,

    output reg  [WIDTH-1:0] result,
    output reg              zero,
    output reg              carry,
    output reg              overflow
);

reg [WIDTH:0] temp;

always @(*) begin

    // Default Values
    result   = 0;
    carry    = 0;
    overflow = 0;

    case(opcode)

        //----------------------------------------------------
        // ADD
        //----------------------------------------------------

        3'b000: begin
            temp     = a + b;
            result   = temp[WIDTH-1:0];
            carry    = temp[WIDTH];
            overflow = (~(a[WIDTH-1]^b[WIDTH-1])) &
                       (result[WIDTH-1]^a[WIDTH-1]);
        end

        //----------------------------------------------------
        // SUB
        //----------------------------------------------------

        3'b001: begin
            temp     = a - b;
            result   = temp[WIDTH-1:0];
            carry    = temp[WIDTH];
            overflow = (a[WIDTH-1]^b[WIDTH-1]) &
                       (result[WIDTH-1]^a[WIDTH-1]);
        end

        //----------------------------------------------------
        // AND
        //----------------------------------------------------

        3'b010:
            result = a & b;

        //----------------------------------------------------
        // OR
        //----------------------------------------------------

        3'b011:
            result = a | b;

        //----------------------------------------------------
        // XOR
        //----------------------------------------------------

        3'b100:
            result = a ^ b;

        //----------------------------------------------------
        // NOT
        //----------------------------------------------------

        3'b101:
            result = ~a;

        //----------------------------------------------------
        // Shift Left
        //----------------------------------------------------

        3'b110:
            result = a << 1;

        //----------------------------------------------------
        // Shift Right
        //----------------------------------------------------

        3'b111:
            result = a >> 1;

        default:
            result = 0;

    endcase

    //--------------------------------------------------------
    // Zero Flag
    //--------------------------------------------------------

    if(result == 0)
        zero = 1'b1;
    else
        zero = 1'b0;

end

endmodule

rtl/counter.v
`timescale 1ns/1ps
//============================================================
// Module : counter
// Description : Parameterized Synchronous Up Counter
// Author : Mihir
//============================================================

module counter #(
    parameter WIDTH = 8
)(
    input  wire             clk,
    input  wire             rst,
    input  wire             enable,

    output reg  [WIDTH-1:0] count,
    output reg              overflow
);

always @(posedge clk) begin

    if (rst) begin
        count     <= {WIDTH{1'b0}};
        overflow  <= 1'b0;
    end

    else if (enable) begin

        if (count == {WIDTH{1'b1}}) begin
            count     <= {WIDTH{1'b0}};
            overflow  <= 1'b1;
        end
        else begin
            count     <= count + 1'b1;
            overflow  <= 1'b0;
        end

    end

    else begin
        count     <= count;
        overflow  <= 1'b0;
    end

end

endmodule

rtl/mini_soc.v
`timescale 1ns/1ps
//============================================================
// Module : mini_soc
// Description : Mini SoC Top Level
// Author : Mihir
//============================================================

module mini_soc(

    //-----------------------------
    // APB Interface
    //-----------------------------

    input wire         PCLK,
    input wire         PRESETn,

    input wire         PSEL,
    input wire         PENABLE,
    input wire         PWRITE,

    input wire [7:0]   PADDR,
    input wire [31:0]  PWDATA,

    output wire [31:0] PRDATA,
    output wire        PREADY,

    //-----------------------------
    // External GPIO
    //-----------------------------

    input wire [7:0] gpio_in

);

//============================================================
// Internal Signals
//============================================================

// Counter

wire [7:0] counter_value;
wire counter_overflow;

// ALU

wire [7:0] alu_result;
wire zero;
wire carry;
wire overflow;

wire [7:0] alu_a;
wire [7:0] alu_b;
wire [2:0] alu_opcode;

// Timer

wire [7:0] timer_load;
wire timer_start;
wire timer_enable;

wire [7:0] timer_count;
wire timer_done;
wire timer_running;

// GPIO

wire [7:0] gpio_direction;
wire [7:0] gpio_write;
wire [7:0] gpio_read;
wire [7:0] gpio_out;

//============================================================
// Counter
//============================================================

counter #(
    .WIDTH(8)
)
u_counter(

    .clk(PCLK),
    .rst(~PRESETn),
    .enable(1'b1),

    .count(counter_value),
    .overflow(counter_overflow)

);

//============================================================
// ALU
//============================================================

alu #(
    .WIDTH(8)
)
u_alu(

    .a(alu_a),
    .b(alu_b),

    .opcode(alu_opcode),

    .result(alu_result),

    .zero(zero),
    .carry(carry),
    .overflow(overflow)

);

//============================================================
// Timer
//============================================================

timer #(
    .WIDTH(8)
)
u_timer(

    .clk(PCLK),
    .rst(~PRESETn),

    .start(timer_start),
    .enable(timer_enable),

    .load_value(timer_load),

    .count(timer_count),
    .done(timer_done),
    .running(timer_running)

);

//============================================================
// GPIO
//============================================================

gpio #(
    .WIDTH(8)
)
u_gpio(

    .clk(PCLK),
    .rst(~PRESETn),

    .write_enable(PSEL && PENABLE && PWRITE && (PADDR==8'h24)),

    .direction(gpio_direction),

    .write_data(gpio_write),

    .gpio_in(gpio_in),

    .gpio_out(gpio_out),
    .gpio_read(gpio_read)

);

//============================================================
// APB Slave
//============================================================

apb_slave u_apb(

    .PCLK(PCLK),
    .PRESETn(PRESETn),

    .PSEL(PSEL),
    .PENABLE(PENABLE),
    .PWRITE(PWRITE),

    .PADDR(PADDR),
    .PWDATA(PWDATA),

    .PRDATA(PRDATA),
    .PREADY(PREADY),

    //---------------- Counter ----------------

    .counter_value(counter_value),

    //---------------- ALU ----------------

    .alu_a(alu_a),
    .alu_b(alu_b),
    .alu_opcode(alu_opcode),

    .alu_result(alu_result),

    //---------------- Timer ----------------

    .timer_load(timer_load),

    .timer_start(timer_start),
    .timer_enable(timer_enable),

    .timer_done(timer_done),
    .timer_running(timer_running),

    //---------------- GPIO ----------------

    .gpio_direction(gpio_direction),
    .gpio_write(gpio_write),

    .gpio_read(gpio_read)

);

endmodule

tb/mini_soc_tb.v
`timescale 1ns/1ps

module mini_soc_tb;

//-----------------------------------------------------
// APB Interface Signals
//-----------------------------------------------------

reg         PCLK;
reg         PRESETn;
reg         PSEL;
reg         PENABLE;
reg         PWRITE;

reg  [7:0]  PADDR;
reg  [31:0] PWDATA;

wire [31:0] PRDATA;
wire        PREADY;

// GPIO External Input

reg [7:0] gpio_in;

//-----------------------------------------------------
// DUT
//-----------------------------------------------------

mini_soc dut (

    .PCLK(PCLK),
    .PRESETn(PRESETn),

    .PSEL(PSEL),
    .PENABLE(PENABLE),
    .PWRITE(PWRITE),

    .PADDR(PADDR),
    .PWDATA(PWDATA),

    .PRDATA(PRDATA),
    .PREADY(PREADY),

    .gpio_in(gpio_in)

);

//-----------------------------------------------------
// Clock Generation
//-----------------------------------------------------

always #5 PCLK = ~PCLK;

//-----------------------------------------------------
// APB WRITE TASK
//-----------------------------------------------------

task apb_write;

input [7:0] addr;
input [31:0] data;

begin

    @(posedge PCLK);

    PSEL    = 1'b1;
    PENABLE = 1'b0;
    PWRITE  = 1'b1;
    PADDR   = addr;
    PWDATA  = data;

    @(posedge PCLK);

    PENABLE = 1'b1;

    @(posedge PCLK);

    PSEL    = 1'b0;
    PENABLE = 1'b0;
    PWRITE  = 1'b0;

end

endtask

//-----------------------------------------------------
// APB READ TASK
//-----------------------------------------------------

task apb_read;

input [7:0] addr;

begin

    @(posedge PCLK);

    PSEL    = 1'b1;
    PENABLE = 1'b0;
    PWRITE  = 1'b0;
    PADDR   = addr;

    @(posedge PCLK);

    PENABLE = 1'b1;

    @(posedge PCLK);

    $display("-------------------------------------");
    $display("READ ADDRESS : 0x%0h", addr);
    $display("READ DATA    : 0x%08h", PRDATA);
    $display("-------------------------------------");

    PSEL    = 1'b0;
    PENABLE = 1'b0;

end

endtask

//-----------------------------------------------------
// Stimulus
//-----------------------------------------------------

initial begin

    //----------------------------
    // Initialize
    //----------------------------

    PCLK     = 0;
    PRESETn  = 0;

    PSEL     = 0;
    PENABLE  = 0;
    PWRITE   = 0;

    PADDR    = 0;
    PWDATA   = 0;

    gpio_in  = 8'h00;

    //----------------------------
    // Waveform
    //----------------------------

    $dumpfile("mini_soc.vcd");
    $dumpvars(0, mini_soc_tb);

    //----------------------------
    // Apply Reset
    //----------------------------

    #20;
    PRESETn = 1;

    //-------------------------------------------------
    // ALU TEST
    //-------------------------------------------------

    // Operand A = 15
    apb_write(8'h04, 32'd15);

    // Operand B = 10
    apb_write(8'h08, 32'd10);

    // ADD
    apb_write(8'h0C, 32'd0);

    #20;

    apb_read(8'h10);

    //-------------------------------------------------
    // SUBTRACT
    //-------------------------------------------------

    apb_write(8'h0C, 32'd1);

    #20;

    apb_read(8'h10);

    //-------------------------------------------------
    // TIMER TEST
    //-------------------------------------------------

    apb_write(8'h14, 32'd8);

    // start=1 enable=1

    apb_write(8'h18, 32'b11);

    #120;

    apb_read(8'h1C);

    //-------------------------------------------------
    // GPIO TEST
    //-------------------------------------------------

    gpio_in = 8'h55;

    // Direction Register

    apb_write(8'h20, 32'hF0);

    // Output Register

    apb_write(8'h24, 32'hA0);

    #20;

    apb_read(8'h28);

    //-------------------------------------------------
    // Counter Test
    //-------------------------------------------------

    #80;

    apb_read(8'h00);

    //-------------------------------------------------
    // Finish
    //-------------------------------------------------

    #50;

    $display("------------------------------------");
    $display(" MINI SOC TEST COMPLETED ");
    $display("------------------------------------");

    $finish;

end

endmodule

waves/mini_soc.vcd
$date
	Fri Jun 26 16:45:04 2026
$end
$version
	Icarus Verilog
$end
$timescale
	1ps
$end
$scope module mini_soc_tb $end
$var wire 1 ! PREADY $end
$var wire 32 " PRDATA [31:0] $end
$var reg 8 # PADDR [7:0] $end
$var reg 1 $ PCLK $end
$var reg 1 % PENABLE $end
$var reg 1 & PRESETn $end
$var reg 1 ' PSEL $end
$var reg 32 ( PWDATA [31:0] $end
$var reg 1 ) PWRITE $end
$var reg 8 * gpio_in [7:0] $end
$scope module dut $end
$var wire 8 + PADDR [7:0] $end
$var wire 1 $ PCLK $end
$var wire 1 % PENABLE $end
$var wire 1 & PRESETn $end
$var wire 1 ' PSEL $end
$var wire 32 , PWDATA [31:0] $end
$var wire 1 ) PWRITE $end
$var wire 8 - gpio_in [7:0] $end
$var wire 1 . zero $end
$var wire 1 / timer_start $end
$var wire 1 0 timer_running $end
$var wire 8 1 timer_load [7:0] $end
$var wire 1 2 timer_enable $end
$var wire 1 3 timer_done $end
$var wire 8 4 timer_count [7:0] $end
$var wire 1 5 overflow $end
$var wire 8 6 gpio_write [7:0] $end
$var wire 8 7 gpio_read [7:0] $end
$var wire 8 8 gpio_out [7:0] $end
$var wire 8 9 gpio_direction [7:0] $end
$var wire 8 : counter_value [7:0] $end
$var wire 1 ; counter_overflow $end
$var wire 1 < carry $end
$var wire 8 = alu_result [7:0] $end
$var wire 3 > alu_opcode [2:0] $end
$var wire 8 ? alu_b [7:0] $end
$var wire 8 @ alu_a [7:0] $end
$var wire 1 ! PREADY $end
$var wire 32 A PRDATA [31:0] $end
$scope module u_alu $end
$var wire 3 B opcode [2:0] $end
$var wire 8 C b [7:0] $end
$var wire 8 D a [7:0] $end
$var parameter 32 E WIDTH $end
$var reg 1 < carry $end
$var reg 1 5 overflow $end
$var reg 8 F result [7:0] $end
$var reg 9 G temp [8:0] $end
$var reg 1 . zero $end
$upscope $end
$scope module u_apb $end
$var wire 8 H PADDR [7:0] $end
$var wire 1 $ PCLK $end
$var wire 1 % PENABLE $end
$var wire 1 & PRESETn $end
$var wire 1 ' PSEL $end
$var wire 32 I PWDATA [31:0] $end
$var wire 1 ) PWRITE $end
$var wire 8 J alu_result [7:0] $end
$var wire 1 0 timer_running $end
$var wire 1 3 timer_done $end
$var wire 8 K gpio_read [7:0] $end
$var wire 8 L counter_value [7:0] $end
$var reg 32 M PRDATA [31:0] $end
$var reg 1 ! PREADY $end
$var reg 8 N alu_a [7:0] $end
$var reg 8 O alu_b [7:0] $end
$var reg 3 P alu_opcode [2:0] $end
$var reg 8 Q gpio_direction [7:0] $end
$var reg 8 R gpio_write [7:0] $end
$var reg 1 2 timer_enable $end
$var reg 8 S timer_load [7:0] $end
$var reg 1 / timer_start $end
$upscope $end
$scope module u_counter $end
$var wire 1 $ clk $end
$var wire 1 T enable $end
$var wire 1 U rst $end
$var parameter 32 V WIDTH $end
$var reg 8 W count [7:0] $end
$var reg 1 ; overflow $end
$upscope $end
$scope module u_gpio $end
$var wire 1 $ clk $end
$var wire 8 X direction [7:0] $end
$var wire 8 Y gpio_in [7:0] $end
$var wire 1 Z rst $end
$var wire 8 [ write_data [7:0] $end
$var wire 1 \ write_enable $end
$var wire 8 ] gpio_read [7:0] $end
$var parameter 32 ^ WIDTH $end
$var reg 8 _ gpio_out [7:0] $end
$scope begin GPIO_READ[0] $end
$var parameter 2 ` k $end
$upscope $end
$scope begin GPIO_READ[1] $end
$var parameter 2 a k $end
$upscope $end
$scope begin GPIO_READ[2] $end
$var parameter 3 b k $end
$upscope $end
$scope begin GPIO_READ[3] $end
$var parameter 3 c k $end
$upscope $end
$scope begin GPIO_READ[4] $end
$var parameter 4 d k $end
$upscope $end
$scope begin GPIO_READ[5] $end
$var parameter 4 e k $end
$upscope $end
$scope begin GPIO_READ[6] $end
$var parameter 4 f k $end
$upscope $end
$scope begin GPIO_READ[7] $end
$var parameter 4 g k $end
$upscope $end
$upscope $end
$scope module u_timer $end
$var wire 1 $ clk $end
$var wire 1 2 enable $end
$var wire 8 h load_value [7:0] $end
$var wire 1 i rst $end
$var wire 1 / start $end
$var parameter 32 j WIDTH $end
$var reg 8 k count [7:0] $end
$var reg 1 3 done $end
$var reg 1 0 running $end
$upscope $end
$upscope $end
$scope task apb_read $end
$var reg 8 l addr [7:0] $end
$upscope $end
$scope task apb_write $end
$var reg 8 m addr [7:0] $end
$var reg 32 n data [31:0] $end
$upscope $end
$upscope $end
$enddefinitions $end
$comment Show the parameter values. $end
$dumpall
b1000 j
b111 g
b110 f
b101 e
b100 d
b11 c
b10 b
b1 a
b0 `
b1000 ^
b1000 V
b1000 E
$end
#0
$dumpvars
bx n
bx m
bx l
bx k
1i
b0 h
bx _
b0 ]
0\
b0 [
1Z
b0 Y
b0 X
bx W
1U
1T
b0 S
b0 R
b0 Q
b0 P
b0 O
b0 N
b0 M
bx L
b0 K
b0 J
b0 I
b0 H
b0 G
b0 F
b0 D
b0 C
b0 B
b0 A
b0 @
b0 ?
b0 >
b0 =
0<
x;
bx :
b0 9
bx 8
b0 7
b0 6
05
bx 4
x3
02
b0 1
x0
0/
1.
b0 -
b0 ,
b0 +
b0 *
0)
b0 (
0'
0&
0%
0$
b0 #
b0 "
0!
$end
#5000
0;
b0 :
b0 L
b0 W
00
03
b0 4
b0 k
b0 8
b0 _
1$
#10000
0$
#15000
1$
#20000
0U
0i
0Z
0$
b1111 n
b100 m
1&
#25000
b1 :
b1 L
b1 W
b1111 (
b1111 ,
b1111 I
b100 #
b100 +
b100 H
1)
1'
1$
#30000
0$
#35000
0.
b1111 =
b1111 F
b1111 J
b1111 G
b1111 @
b1111 D
b1111 N
1!
b10 :
b10 L
b10 W
1%
1$
#40000
0$
#45000
0!
b11 :
b11 L
b11 W
b1010 n
b1000 m
0)
0%
0'
1$
#50000
0$
#55000
b100 :
b100 L
b100 W
b1010 (
b1010 ,
b1010 I
b1000 #
b1000 +
b1000 H
1)
1'
1$
#60000
0$
#65000
b11001 G
b11001 =
b11001 F
b11001 J
b1010 ?
b1010 C
b1010 O
1!
b101 :
b101 L
b101 W
1%
1$
#70000
0$
#75000
0!
b110 :
b110 L
b110 W
b0 n
b1100 m
0)
0%
0'
1$
#80000
0$
#85000
b111 :
b111 L
b111 W
b0 (
b0 ,
b0 I
b1100 #
b1100 +
b1100 H
1)
1'
1$
#90000
0$
#95000
1!
b1000 :
b1000 L
b1000 W
1%
1$
#100000
0$
#105000
0!
b1001 :
b1001 L
b1001 W
0)
0%
0'
1$
#110000
0$
#115000
b1010 :
b1010 L
b1010 W
1$
#120000
0$
#125000
b1011 :
b1011 L
b1011 W
b11001 "
b11001 A
b11001 M
b10000 #
b10000 +
b10000 H
1'
1$
b10000 l
#130000
0$
#135000
b11001 "
b11001 A
b11001 M
1!
b1100 :
b1100 L
b1100 W
1%
1$
#140000
0$
#145000
0!
b1101 :
b1101 L
b1101 W
b0 "
b0 A
b0 M
b1 n
0%
0'
1$
#150000
0$
#155000
b1110 :
b1110 L
b1110 W
b1 (
b1 ,
b1 I
b1100 #
b1100 +
b1100 H
1)
1'
1$
#160000
0$
#165000
b101 G
b101 =
b101 F
b101 J
b1 >
b1 B
b1 P
1!
b1111 :
b1111 L
b1111 W
1%
1$
#170000
0$
#175000
0!
b10000 :
b10000 L
b10000 W
0)
0%
0'
1$
#180000
0$
#185000
b10001 :
b10001 L
b10001 W
1$
#190000
0$
#195000
b10010 :
b10010 L
b10010 W
b101 "
b101 A
b101 M
b10000 #
b10000 +
b10000 H
1'
1$
#200000
0$
#205000
b101 "
b101 A
b101 M
1!
b10011 :
b10011 L
b10011 W
1%
1$
#210000
0$
#215000
0!
b10100 :
b10100 L
b10100 W
b0 "
b0 A
b0 M
b1000 n
b10100 m
0%
0'
1$
#220000
0$
#225000
b10101 :
b10101 L
b10101 W
b1000 (
b1000 ,
b1000 I
b10100 #
b10100 +
b10100 H
1)
1'
1$
#230000
0$
#235000
b1000 1
b1000 S
b1000 h
1!
b10110 :
b10110 L
b10110 W
1%
1$
#240000
0$
#245000
0!
b10111 :
b10111 L
b10111 W
b11 n
b11000 m
0)
0%
0'
1$
#250000
0$
#255000
b11000 :
b11000 L
b11000 W
b11 (
b11 ,
b11 I
b11000 #
b11000 +
b11000 H
1)
1'
1$
#260000
0$
#265000
12
1/
1!
b11001 :
b11001 L
b11001 W
1%
1$
#270000
0$
#275000
0/
0!
10
b1000 4
b1000 k
b11010 :
b11010 L
b11010 W
0)
0%
0'
1$
#280000
0$
#285000
b11011 :
b11011 L
b11011 W
b111 4
b111 k
1$
#290000
0$
#295000
b110 4
b110 k
b11100 :
b11100 L
b11100 W
1$
#300000
0$
#305000
b11101 :
b11101 L
b11101 W
b101 4
b101 k
1$
#310000
0$
#315000
b100 4
b100 k
b11110 :
b11110 L
b11110 W
1$
#320000
0$
#325000
b11111 :
b11111 L
b11111 W
b11 4
b11 k
1$
#330000
0$
#335000
b10 4
b10 k
b100000 :
b100000 L
b100000 W
1$
#340000
0$
#345000
b100001 :
b100001 L
b100001 W
b1 4
b1 k
1$
#350000
0$
#355000
b0 4
b0 k
b100010 :
b100010 L
b100010 W
1$
#360000
0$
#365000
b100011 :
b100011 L
b100011 W
13
00
1$
#370000
0$
#375000
b100100 :
b100100 L
b100100 W
1$
#380000
0$
#385000
b100101 :
b100101 L
b100101 W
1$
#390000
0$
#395000
b100110 :
b100110 L
b100110 W
b1 "
b1 A
b1 M
b11100 #
b11100 +
b11100 H
1'
1$
b11100 l
#400000
0$
#405000
b1 "
b1 A
b1 M
1!
b100111 :
b100111 L
b100111 W
1%
1$
#410000
0$
#415000
0!
b101000 :
b101000 L
b101000 W
b1010101 7
b1010101 K
b1010101 ]
b0 "
b0 A
b0 M
b11110000 n
b100000 m
b1010101 *
b1010101 -
b1010101 Y
0%
0'
1$
#420000
0$
#425000
b101001 :
b101001 L
b101001 W
b11110000 (
b11110000 ,
b11110000 I
b100000 #
b100000 +
b100000 H
1)
1'
1$
#430000
0$
#435000
b101 7
b101 K
b101 ]
b11110000 9
b11110000 Q
b11110000 X
1!
b101010 :
b101010 L
b101010 W
1%
1$
#440000
0$
#445000
0!
b101011 :
b101011 L
b101011 W
b10100000 n
b100100 m
0)
0%
0'
1$
#450000
0$
#455000
b101100 :
b101100 L
b101100 W
b10100000 (
b10100000 ,
b10100000 I
b100100 #
b100100 +
b100100 H
1)
1'
1$
#460000
0$
#465000
b10100000 6
b10100000 R
b10100000 [
1!
b101101 :
b101101 L
b101101 W
1\
1%
1$
#470000
0$
#475000
b10100101 7
b10100101 K
b10100101 ]
0!
b10100000 8
b10100000 _
b101110 :
b101110 L
b101110 W
0\
0)
0%
0'
1$
#480000
0$
#485000
b101111 :
b101111 L
b101111 W
1$
#490000
0$
#495000
b110000 :
b110000 L
b110000 W
b10100101 "
b10100101 A
b10100101 M
b101000 #
b101000 +
b101000 H
1'
1$
b101000 l
#500000
0$
#505000
b10100101 "
b10100101 A
b10100101 M
1!
b110001 :
b110001 L
b110001 W
1%
1$
#510000
0$
#515000
0!
b110010 :
b110010 L
b110010 W
b0 "
b0 A
b0 M
0%
0'
1$
#520000
0$
#525000
b110011 :
b110011 L
b110011 W
1$
#530000
0$
#535000
b110100 :
b110100 L
b110100 W
1$
#540000
0$
#545000
b110101 :
b110101 L
b110101 W
1$
#550000
0$
#555000
b110110 :
b110110 L
b110110 W
1$
#560000
0$
#565000
b110111 :
b110111 L
b110111 W
1$
#570000
0$
#575000
b111000 :
b111000 L
b111000 W
1$
#580000
0$
#585000
b111001 :
b111001 L
b111001 W
1$
#590000
0$
#595000
b111010 :
b111010 L
b111010 W
b111010 "
b111010 A
b111010 M
b0 #
b0 +
b0 H
1'
1$
b0 l
#600000
0$
#605000
b111011 "
b111011 A
b111011 M
1!
b111011 :
b111011 L
b111011 W
1%
1$
#610000
0$
#615000
0!
b111100 :
b111100 L
b111100 W
b0 "
b0 A
b0 M
0%
0'
1$
#620000
0$
#625000
b111101 :
b111101 L
b111101 W
1$
#630000
0$
#635000
b111110 :
b111110 L
b111110 W
1$
#640000
0$
#645000
b111111 :
b111111 L
b111111 W
1$
#650000
0$
#655000
b1000000 :
b1000000 L
b1000000 W
1$
#660000
0$
#665000
b1000001 :
b1000001 L
b1000001 W
1$
